gcbinspy/__init__.py
gcbinspy/example.py
gcbinspy/gcbinspy.py
gcbinspy-0.0.4.dist-info/LICENSE.md
gcbinspy-0.0.4.dist-info/METADATA
gcbinspy-0.0.4.dist-info/WHEEL
gcbinspy-0.0.4.dist-info/top_level.txt
gcbinspy-0.0.4.dist-info/RECORD
