Metadata-Version: 2.1
Name: gcbinspy
Version: 0.0.4
Summary: Gold Coast bin days
Author-email: poroping <poroping@github.com>
Project-URL: Homepage, https://github.com/poroping/gcbinspy
Requires-Python: >=3.10.0
License-File: LICENSE.md
Requires-Dist: requests
Requires-Dist: python-dateutil
Requires-Dist: beautifulsoup4
